apns2/__init__.py
apns2/client.py
apns2/credentials.py
apns2/errors.py
apns2/payload.py
compat_fork_apns2-0.8.0.dist-info/LICENSE
compat_fork_apns2-0.8.0.dist-info/METADATA
compat_fork_apns2-0.8.0.dist-info/WHEEL
compat_fork_apns2-0.8.0.dist-info/RECORD
